twistedlilypad/__init__.py
twistedlilypad/protocol.py
twistedlilypad/packets/__init__.py
twistedlilypad/packets/abstract_packet.py
twistedlilypad/packets/keep_alive_packet.py
twistedlilypad/packets/message_event_packet.py
twistedlilypad/packets/player_event_packet.py
twistedlilypad/packets/redirect_event_packet.py
twistedlilypad/packets/request_packet.py
twistedlilypad/packets/result_packet.py
twistedlilypad/packets/server_event_packet.py
twistedlilypad/requests/__init__.py
twistedlilypad/requests/abstract_request.py
twistedlilypad/requests/as_proxy_request.py
twistedlilypad/requests/as_server_request.py
twistedlilypad/requests/authenticate_request.py
twistedlilypad/requests/get_details_request.py
twistedlilypad/requests/get_players_request.py
twistedlilypad/requests/get_salt_request.py
twistedlilypad/requests/get_who_am_i_request.py
twistedlilypad/requests/message_request.py
twistedlilypad/requests/notify_player_request.py
twistedlilypad/requests/redirect_request.py
twistedlilypad/results/__init__.py
twistedlilypad/results/abstract_result.py
twistedlilypad/results/as_proxy_result.py
twistedlilypad/results/as_server_result.py
twistedlilypad/results/authenticate_result.py
twistedlilypad/results/get_details_result.py
twistedlilypad/results/get_players_result.py
twistedlilypad/results/get_salt_result.py
twistedlilypad/results/get_who_am_i_result.py
twistedlilypad/results/message_result.py
twistedlilypad/results/notify_player_result.py
twistedlilypad/results/redirect_result.py
twistedlilypad/utilities/__init__.py
twistedlilypad/utilities/decoder_utilities.py
twistedlilypad/utilities/encoder_utilities.py
twistedlilypad/utilities/packet_utilties.py
twistedlilypad-2.0.0.dist-info/DESCRIPTION.rst
twistedlilypad-2.0.0.dist-info/METADATA
twistedlilypad-2.0.0.dist-info/RECORD
twistedlilypad-2.0.0.dist-info/WHEEL
twistedlilypad-2.0.0.dist-info/metadata.json
twistedlilypad-2.0.0.dist-info/top_level.txt
