Metadata-Version: 2.0
Name: twistedlilypad
Version: 2.0.0
Summary: An implementation of the lilypad protocol in python
Home-page: https://github.com/flaminscotsman/TwistedLilypad
Author: Alasdair Scott
Author-email: ali+python@flaminscotsman.co.uk
License: MIT
Keywords: lilypad minecraft
Platform: UNKNOWN
Classifier: Development Status :: 3 - Alpha
Classifier: Intended Audience :: Developers
Classifier: Topic :: Software Development
Classifier: License :: OSI Approved :: MIT License
Classifier: Programming Language :: Python :: 2
Classifier: Programming Language :: Python :: 2.7
Classifier: Programming Language :: Python :: 3
Requires-Dist: twisted
